Metadata-Version: 2.1
Name: CoreEngineX
Version: 0.0.1
Summary: CoreEngineX fetches and displays Python files from a directory and sub-directories in a CLI menu. It executes the files sequentially and offers the option to check their pylint score.
Home-page: https://github.com/4akhilkumar/coreenginex
Author: Sai Akhil Kumar Reddy N
Author-email: 4akhilkumar@gmail.com
License: MIT
Keywords: Python,Files,Execution,CoreEngineX,CLI,Command Line Interface,Menu,Pylint
Classifier: Development Status :: 4 - Beta
Classifier: Intended Audience :: Developers
Classifier: License :: OSI Approved :: MIT License
Classifier: Programming Language :: Python :: 3
Classifier: Programming Language :: Python :: 3.7
Classifier: Programming Language :: Python :: 3.8
Classifier: Programming Language :: Python :: 3.9
Classifier: Programming Language :: Python :: 3.10
Classifier: Programming Language :: Python :: 3.11
License-File: LICENSE
